{
	"严禧哲": {
		"年级": "18",
		"组别": "前端组",
		"count": {
			"num": 0,
			"data": [],
			"requireNum": 5,
			"pass": false
		}
	},
	"何彦涛": {
		"年级": "17",
		"组别": "数码组",
		"count": {
			"num": 1,
			"data": ["2018-09-04"],
			"requireNum": 5,
			"pass": false
		}
	},
	"薛玥": {
		"年级": "17",
		"组别": "数码组",
		"count": {
			"num": 0,
			"data": [],
			"requireNum": 5,
			"pass": false
		}
	},
	"王羿": {
		"年级": "17",
		"组别": "数码组",
		"count": {
			"num": 1,
			"data": ["2018-09-03"],
			"requireNum": 5,
			"pass": false
		}
	},
	"林胤达": {
		"年级": "17",
		"组别": "编程组",
		"count": {
			"num": 3,
			"data": ["2018-09-04", "2018-09-03", "2018-08-31"],
			"requireNum": 5,
			"pass": false
		}
	},
	"李智麟": {
		"年级": "17",
		"组别": "编程组",
		"count": {
			"num": 2,
			"data": ["2018-09-04", "2018-09-03"],
			"requireNum": 5,
			"pass": false
		}
	},
	"吕子丰": {
		"年级": "17",
		"组别": "编程组",
		"count": {
			"num": 2,
			"data": ["2018-09-04", "2018-09-03"],
			"requireNum": 5,
			"pass": false
		}
	},
	"区瑞敏": {
		"年级": "17",
		"组别": "编程组",
		"count": {
			"num": 2,
			"data": ["2018-09-04", "2018-09-03"],
			"requireNum": 5,
			"pass": false
		}
	},
	"杨立凡": {
		"年级": "17",
		"组别": "前端组",
		"count": {
			"num": 1,
			"data": ["2018-09-03"],
			"requireNum": 5,
			"pass": false
		}
	},
	"谈正起": {
		"年级": "16",
		"组别": "网管组",
		"count": {
			"num": 0,
			"data": [],
			"requireNum": 5,
			"pass": false
		}
	},
	"杨利婷": {
		"年级": "16",
		"组别": "网管组",
		"count": {
			"num": 2,
			"data": ["2018-09-04", "2018-09-03"],
			"requireNum": 5,
			"pass": false
		}
	},
	"贺泽芃": {
		"年级": "16",
		"组别": "网管组",
		"count": {
			"num": 10,
			"data": ["2018-09-04", "2018-09-03", "2018-08-20", "2018-08-17", "2018-08-15", "2018-08-14", "2018-08-13", "2018-08-11", "2018-08-10", "2018-08-06"],
			"requireNum": 5,
			"pass": true
		}
	},
	"邓泳锋": {
		"年级": "16",
		"组别": "前端组",
		"count": {
			"num": 6,
			"data": ["2018-09-04", "2018-09-03", "2018-08-17", "2018-08-13", "2018-08-08", "2018-08-06"],
			"requireNum": 5,
			"pass": true
		}
	},
	"冯泽伦": {
		"年级": "16",
		"组别": "前端组",
		"count": {
			"num": 2,
			"data": ["2018-09-04", "2018-09-03"],
			"requireNum": 5,
			"pass": false
		}
	},
	"陈浩林": {
		"年级": "16",
		"组别": "编程组",
		"count": {
			"num": 8,
			"data": ["2018-09-05", "2018-09-03", "2018-08-29", "2018-08-15", "2018-08-14", "2018-08-13", "2018-08-07", "2018-08-06"],
			"requireNum": 5,
			"pass": true
		}
	},
	"张春祥": {
		"年级": "16",
		"组别": "编程组",
		"count": {
			"num": 13,
			"data": ["2018-09-04", "2018-08-22", "2018-08-21", "2018-08-20", "2018-08-16", "2018-08-15", "2018-08-14", "2018-08-13", "2018-08-10", "2018-08-09", "2018-08-08", "2018-08-07", "2018-08-06"],
			"requireNum": 5,
			"pass": true
		}
	},
	"李佳新": {
		"年级": "16",
		"组别": "编程组",
		"count": {
			"num": 2,
			"data": ["2018-09-04", "2018-09-03"],
			"requireNum": 5,
			"pass": false
		}
	},
	"曹睿之": {
		"年级": "16",
		"组别": "编程组",
		"count": {
			"num": 18,
			"data": ["2018-08-24", "2018-08-23", "2018-08-22", "2018-08-21", "2018-08-20", "2018-08-17", "2018-08-16", "2018-08-15", "2018-08-14", "2018-08-13", "2018-08-10", "2018-08-09", "2018-08-08", "2018-08-07", "2018-08-06", "2018-08-03", "2018-08-02", "2018-08-01"],
			"requireNum": 5,
			"pass": true
		}
	},
	"夏天成": {
		"年级": "16",
		"组别": "编程组",
		"count": {
			"num": 11,
			"data": ["2018-09-03", "2018-08-16", "2018-08-17", "2018-08-15", "2018-08-14", "2018-08-13", "2018-08-10", "2018-08-09", "2018-08-08", "2018-08-07", "2018-08-06"],
			"requireNum": 5,
			"pass": true
		}
	},
	"曹越洋": {
		"年级": "16",
		"组别": "编程组",
		"count": {
			"num": 2,
			"data": ["2018-09-04", "2018-09-03"],
			"requireNum": 5,
			"pass": false
		}
	},
	"林秘海": {
		"年级": "16",
		"组别": "前端组",
		"count": {
			"num": 0,
			"data": [],
			"requireNum": 5,
			"pass": false
		}
	},
	"黄雅诗": {
		"年级": "16",
		"组别": "设计组",
		"count": {
			"num": 9,
			"data": ["2018-09-05", "2018-09-04", "2018-09-03", "2018-08-20", "2018-08-15", "2018-08-14", "2018-08-13", "2018-08-07", "2018-08-06"],
			"requireNum": 5,
			"pass": true
		}
	},
	"黄依华": {
		"年级": "16",
		"组别": "设计组",
		"count": {
			"num": 3,
			"data": ["2018-09-04", "2018-09-03", "2018-08-31"],
			"requireNum": 5,
			"pass": false
		}
	},
	"文海平": {
		"年级": "15",
		"组别": "网管组",
		"count": {
			"num": 22,
			"data": ["2018-09-04", "2018-09-03", "2018-08-31", "2018-08-30", "2018-08-29", "2018-08-28", "2018-08-27", "2018-08-24", "2018-08-23", "2018-08-22", "2018-08-21", "2018-08-20", "2018-08-17", "2018-08-16", "2018-08-15", "2018-08-14", "2018-08-13", "2018-08-10", "2018-08-09", "2018-08-08", "2018-08-07", "2018-08-06"],
			"requireNum": 5,
			"pass": true
		}
	},
	"罗丽苹": {
		"年级": "15",
		"组别": "网管组",
		"count": {
			"num": 2,
			"data": ["2018-09-04", "2010-09-03"],
			"requireNum": 5,
			"pass": false
		}
	},
	"欧阳婕": {
		"年级": "15",
		"组别": "数码组",
		"count": {
			"num": 2,
			"data": ["2018-09-04", "2018-09-03"],
			"requireNum": 5,
			"pass": false
		}
	},
	"江嘉玲": {
		"年级": "15",
		"组别": "数码组",
		"count": {
			"num": 0,
			"data": [],
			"requireNum": 5,
			"pass": false
		}
	},
	"赵婷婷": {
		"年级": "15",
		"组别": "数码组",
		"count": {
			"num": 0,
			"data": [],
			"requireNum": 5,
			"pass": false
		}
	},
	"卢向东": {
		"年级": "15",
		"组别": "编程组",
		"count": {
			"num": 0,
			"data": [],
			"requireNum": 5,
			"pass": false
		}
	},
	"雷雨": {
		"年级": "15",
		"组别": "前端组",
		"count": {
			"num": 2,
			"data": ["2018-09-04", "2018-09-03"],
			"requireNum": 5,
			"pass": false
		}
	},
	"郑培钦": {
		"年级": "15",
		"组别": "前端组",
		"count": {
			"num": 0,
			"data": [],
			"requireNum": 5,
			"pass": false
		}
	},
	"宋婧仪": {
		"年级": "15",
		"组别": "前端组",
		"count": {
			"num": 0,
			"data": [],
			"requireNum": 5,
			"pass": false
		}
	},
	"范敬一": {
		"年级": "15",
		"组别": "设计组",
		"count": {
			"num": 2,
			"data": ["2018-09-04", "2018-09-03"],
			"requireNum": 5,
			"pass": false
		}
	},
	"胡慧盈": {
		"年级": "15",
		"组别": "设计组",
		"count": {
			"num": 0,
			"data": [],
			"requireNum": 5,
			"pass": false
		}
	},
	"俞霏霏": {
		"年级": "15",
		"组别": "设计组",
		"count": {
			"num": 7,
			"data": ["2018-09-03", "2018-08-13", "2018-08-10", "2018-08-09", "2018-08-08", "2018-08-07", "2018-08-06"],
			"requireNum": 5,
			"pass": true
		}
	}
}